gitflic
