Metadata-Version: 2.1
Name: gitflic-bb
Version: 1.112
Summary: GitflicApi-bb wrapper
Home-page: https://gitflic.ru/user/dikola
Author: Dikola
Author-email: chi.nik1304@gmail.com
License: MIT
Project-URL: Source, https://gitflic.ru/user/dikola
Platform: UNKNOWN
Classifier: Programming Language :: Python :: 3
Classifier: License :: OSI Approved :: MIT License
Classifier: Operating System :: OS Independent
Requires-Python: >=3.7
License-File: LICENSE
